MANIFEST.in
README.md
setup.py
UW_RestClients_WhenIWork.egg-info/PKG-INFO
UW_RestClients_WhenIWork.egg-info/SOURCES.txt
UW_RestClients_WhenIWork.egg-info/dependency_links.txt
UW_RestClients_WhenIWork.egg-info/requires.txt
UW_RestClients_WhenIWork.egg-info/top_level.txt
uw_wheniwork/VERSION
uw_wheniwork/__init__.py
uw_wheniwork/account.py
uw_wheniwork/dao.py
uw_wheniwork/locations.py
uw_wheniwork/messages.py
uw_wheniwork/models.py
uw_wheniwork/positions.py
uw_wheniwork/requests.py
uw_wheniwork/shifts.py
uw_wheniwork/sites.py
uw_wheniwork/test.py
uw_wheniwork/users.py
uw_wheniwork/util.py
uw_wheniwork/resources/wheniwork/file/2/account/index.html
uw_wheniwork/resources/wheniwork/file/2/locations/136
uw_wheniwork/resources/wheniwork/file/2/locations/index.html
uw_wheniwork/resources/wheniwork/file/2/positions/32
uw_wheniwork/resources/wheniwork/file/2/positions/index.html
uw_wheniwork/resources/wheniwork/file/2/requests/_end_2012-04-30_page_0_start_2012-03-01
uw_wheniwork/resources/wheniwork/file/2/requests/_end_2012-05-30_page_0_start_2012-05-01
uw_wheniwork/resources/wheniwork/file/2/requests/_end_2012-05-30_page_1_start_2012-05-01
uw_wheniwork/resources/wheniwork/file/2/requests/_end_2012-05-30_page_2_start_2012-05-01
uw_wheniwork/resources/wheniwork/file/2/shifts/_end_2014-03-08_23_59_59_location_id_1_start_2014-03-05_00_00_00
uw_wheniwork/resources/wheniwork/file/2/shifts/_ids_1337
uw_wheniwork/resources/wheniwork/file/2/shifts/index.html
uw_wheniwork/resources/wheniwork/file/2/sites/9
uw_wheniwork/resources/wheniwork/file/2/sites/index.html
uw_wheniwork/resources/wheniwork/file/2/users/4364
uw_wheniwork/resources/wheniwork/file/2/users/_
uw_wheniwork/tests/__init__.py
uw_wheniwork/tests/test_accounts.py
uw_wheniwork/tests/test_locations.py
uw_wheniwork/tests/test_positions.py
uw_wheniwork/tests/test_requests.py
uw_wheniwork/tests/test_shifts.py
uw_wheniwork/tests/test_sites.py
uw_wheniwork/tests/test_users.py