Metadata-Version: 1.1
Name: UW-RestClients-WhenIWork
Version: 1.0.1
Summary: Client for the WhenIWork REST API
Home-page: https://github.com/uw-it-cte/uw-restclients-wheniwork
Author: UNKNOWN
Author-email: UNKNOWN
License: Apache License, Version 2.0
Platform: UNKNOWN
Classifier: Environment :: Web Environment
Classifier: Intended Audience :: Developers
Classifier: License :: OSI Approved :: Apache Software License
Classifier: Operating System :: OS Independent
Classifier: Programming Language :: Python
Classifier: Programming Language :: Python :: 2.7
Classifier: Programming Language :: Python :: 3.6
Classifier: Topic :: Office/Business :: Scheduling
